{
  "db_name": "PostgreSQL",
  "query": "SELECT status::text, tx_hash FROM bid WHERE id = $1",
  "describe": {
    "columns": [
      {
        "ordinal": 0,
        "name": "status",
        "type_info": "Text"
      },
      {
        "ordinal": 1,
        "name": "tx_hash",
        "type_info": "Bytea"
      }
    ],
    "parameters": {
      "Left": [
        "Uuid"
      ]
    },
    "nullable": [
      null,
      true
    ]
  },
  "hash": "d3bf77d55e359e5700ac7732c3a70eac68221a42277c60d21789e618e9cec3d8"
}
